setup.py
as_list/__init__.py
as_list.egg-info/PKG-INFO
as_list.egg-info/SOURCES.txt
as_list.egg-info/dependency_links.txt
as_list.egg-info/pbr.json
as_list.egg-info/top_level.txt