Metadata-Version: 1.1
Name: as-list
Version: 0.2.1
Summary: Verifies if giving object is list or tuple; if not returns a list with it as single element
Home-page: https://github.com/victor-torres/as_list
Author: Victor Torres
Author-email: vpaivatorres@gmail.com
License: UNKNOWN
Platform: UNKNOWN
Classifier: Intended Audience :: Developers
Classifier: Topic :: Software Development :: Build Tools
Classifier: Development Status :: 2 - Pre-Alpha
Classifier: Programming Language :: Python
Classifier: Programming Language :: Python :: 2
Classifier: Programming Language :: Python :: 2.7
Classifier: Programming Language :: Python :: 3
Classifier: Programming Language :: Python :: 3.3
